{
    "actorList": [
        "Martina Gedeck", 
        "Ulrich M\u00fche", 
        "Sebastian Koch", 
        "Ulrich Tukur", 
        "Thomas Thieme", 
        "Hans-Uwe Bauer", 
        "Volkmar Kleinert", 
        "Matthias Brenner", 
        "Charly H\u00fcbner", 
        "Herbert Knaup", 
        "Bastian Trost", 
        "Marie Gruber", 
        "Volker Michalowski", 
        "Werner Daehn", 
        "Martin Brambach", 
        "Hubertus Hartmann", 
        "Thomas Arnold", 
        "Hinnerk Sch\u00f6nemann", 
        "Paul Fa\u00dfnacht", 
        "Ludwig Blochberger", 
        "Paul Maximilian Sch\u00fcller", 
        "Susanna Kraus", 
        "Gabi Fleming", 
        "Michael Gerber", 
        "Fabian von Klitzing", 
        "Harald Polzin", 
        "Sheri Hagen", 
        "Gitta Schweigh\u00f6fer", 
        "Elja-Dusa Kedves", 
        "Hildegard Schroedter", 
        "Inga Birkenfeld", 
        "Philipp Kewenig", 
        "Jens Wassermann", 
        "Ernst-Ludwig Petrowsky", 
        "Manfred Ludwig Sextett", 
        "Kai Ivo Baulitz", 
        "Ralf Ehrlich", 
        "Anabelle D. Munro", 
        "Klaus M\u00fcnster"
    ], 
    "director": [
        "Florian Henckel von Donnersmarck"
    ], 
    "genres": [
        "Drama", 
        "Thriller"
    ], 
    "name": "Das Leben der Anderen", 
    "plot": "In 1984 East Berlin, an agent of the secret police, conducting surveillance on a writer and his lover, finds himself becoming increasingly absorbed by their lives.", 
    "rating": 8.5, 
    "releaseDate": "15 March 2006 (Berlin)\n (premiere)", 
    "type": "movie"
}